<?xml version="1.0" encoding="UTF-8"?>
<objects serializationModel="Studio.02.02.00">
	<object class="EncodingSetting" id="{0d87c925-951c-45a0-9d13-197b24847c64}">
		<property name="encodingFormat">
			<value>3</value>
		</property>
		<property name="quality">
			<value>21</value>
		</property>
		<property name="sampleRate">
			<value>38000</value>
		</property>
		<relationship name="platform">
			<destination>{b9e61891-92e4-409e-a16f-463a532ececc}</destination>
		</relationship>
		<relationship name="encodable">
			<destination>{efed1154-62e1-4d15-959a-bac8ba0c8e81}</destination>
		</relationship>
	</object>
</objects>
