<?xml version="1.0" encoding="UTF-8"?>
<objects serializationModel="Studio.02.02.00">
	<object class="EncodingSetting" id="{60410af1-32fc-403d-be2f-4191a1a0e482}">
		<property name="encodingFormat">
			<value>3</value>
		</property>
		<property name="quality">
			<value>21</value>
		</property>
		<property name="sampleRate">
			<value>38000</value>
		</property>
		<relationship name="platform">
			<destination>{b9e61891-92e4-409e-a16f-463a532ececc}</destination>
		</relationship>
		<relationship name="encodable">
			<destination>{ccae1033-545e-4f59-b381-5c19f02793e1}</destination>
		</relationship>
	</object>
</objects>
